unitsofmeasure/__init__.py
unitsofmeasure/accepted.py
unitsofmeasure/base.py
unitsofmeasure/binprefix.py
unitsofmeasure/decprefix.py
unitsofmeasure/derived.py
unitsofmeasure/test/__init__.py
unitsofmeasure/test/test_accepted.py
unitsofmeasure/test/test_base.py
unitsofmeasure/test/test_binprefix.py
unitsofmeasure/test/test_decprefix.py
unitsofmeasure/test/test_derived.py
unitsofmeasure/test/test_dimension.py
unitsofmeasure/test/test_prefix.py
unitsofmeasure/test/test_si_units.py
unitsofmeasure/test/test_unit.py
unitsofmeasure/test/test_unitmap.py
units_of_measure-1.2.0.dist-info/METADATA
units_of_measure-1.2.0.dist-info/WHEEL
units_of_measure-1.2.0.dist-info/licenses/LICENSE
units_of_measure-1.2.0.dist-info/RECORD
