Metadata-Version: 2.3
Name: units-of-measure
Version: 1.2.0
Summary: Units of Measure
Project-URL: Homepage, https://github.com/gerald-scharitzer/units-of-measure
Project-URL: Bug Tracker, https://github.com/gerald-scharitzer/units-of-measure/issues
Project-URL: Source Code, https://github.com/gerald-scharitzer/units-of-measure
Author: Gerald Scharitzer
License-File: LICENSE
Classifier: License :: OSI Approved :: BSD License
Classifier: Operating System :: OS Independent
Classifier: Programming Language :: Python :: 3
Requires-Python: >=3.9
